trackremux/__init__.py
trackremux/__main__.py
trackremux/core/__init__.py
trackremux/core/batch.py
trackremux/core/converter.py
trackremux/core/languages.py
trackremux/core/models.py
trackremux/core/preview.py
trackremux/core/probe.py
trackremux/core/scanner.py
trackremux/tui/__init__.py
trackremux/tui/app.py
trackremux/tui/batch_progress.py
trackremux/tui/batch_selector.py
trackremux/tui/constants.py
trackremux/tui/editor.py
trackremux/tui/explorer.py
trackremux/tui/formatters.py
trackremux/tui/progress.py
trackremux-0.6.0.dist-info/licenses/LICENSE
trackremux-0.6.0.dist-info/METADATA
trackremux-0.6.0.dist-info/WHEEL
trackremux-0.6.0.dist-info/entry_points.txt
trackremux-0.6.0.dist-info/top_level.txt
trackremux-0.6.0.dist-info/RECORD
