Metadata-Version: 2.4
Name: trackremux
Version: 0.6.0
Summary: A powerful TUI tool to interactively select and remux audio/subtitle tracks from video files
Author-email: Yevgen Antymyrov <me@antimirov.net>
License-Expression: MIT
Project-URL: homepage, https://github.com/antimirov/trackremux
Project-URL: issues, https://github.com/antimirov/trackremux/issues
Project-URL: changelog, https://github.com/antimirov/trackremux/blob/main/CHANGELOG.md
Requires-Python: >=3.10
License-File: LICENSE
Dynamic: license-file
